tgvoip/utils.py
tgvoip/_tgvoip.pyi
tgvoip/_tgvoip.cpython-313-x86_64-linux-musl.so
tgvoip/tgvoip.py
tgvoip/__init__.py
stefano_pytgvoip-0.0.7.5.dist-info/WHEEL
stefano_pytgvoip-0.0.7.5.dist-info/top_level.txt
stefano_pytgvoip-0.0.7.5.dist-info/METADATA
stefano_pytgvoip-0.0.7.5.dist-info/RECORD
stefano_pytgvoip-0.0.7.5.dist-info/licenses/NOTICE
stefano_pytgvoip-0.0.7.5.dist-info/licenses/COPYING.lesser
stefano_pytgvoip-0.0.7.5.dist-info/licenses/COPYING
stefano_pytgvoip.libs/libopus-e96458dd.so.0.9.0
stefano_pytgvoip.libs/libstdc++-496613c0.so.6.0.32
stefano_pytgvoip.libs/libgcc_s-a3a07607.so.1
stefano_pytgvoip.libs/libcrypto-17f1133f.so.3
